hypyxel/__init__.py
hypyxel/api.py
hypyxel/errors.py
hypyxel/utils.py
Hypyxel-0.1.0.post5.dist-info/LICENSE
Hypyxel-0.1.0.post5.dist-info/METADATA
Hypyxel-0.1.0.post5.dist-info/WHEEL
Hypyxel-0.1.0.post5.dist-info/top_level.txt
Hypyxel-0.1.0.post5.dist-info/RECORD
