Metadata-Version: 2.1
Name: Hypyxel
Version: 0.1.0.post5
Summary: An easy-to-use python wrapper for the Hypixel API
Home-page: https://github.com/CraziiAce/Hypyxel
Author: CraziiAce
Author-email: teddyjraz@gmail.com
License: UNKNOWN
Platform: UNKNOWN
Classifier: Programming Language :: Python :: 3
Classifier: License :: OSI Approved :: GNU General Public License v3 (GPLv3)
Classifier: Operating System :: OS Independent
Requires-Python: >=3.6
